iris_oc_mapper/.mypy_cache/.gitignore
iris_oc_mapper/.mypy_cache/3.13/@plugins_snapshot.json
iris_oc_mapper/.mypy_cache/3.13/_ast.data.json
iris_oc_mapper/.mypy_cache/3.13/_ast.meta.json
iris_oc_mapper/.mypy_cache/3.13/_codecs.data.json
iris_oc_mapper/.mypy_cache/3.13/_codecs.meta.json
iris_oc_mapper/.mypy_cache/3.13/_collections_abc.data.json
iris_oc_mapper/.mypy_cache/3.13/_collections_abc.meta.json
iris_oc_mapper/.mypy_cache/3.13/_frozen_importlib.data.json
iris_oc_mapper/.mypy_cache/3.13/_frozen_importlib.meta.json
iris_oc_mapper/.mypy_cache/3.13/_frozen_importlib_external.data.json
iris_oc_mapper/.mypy_cache/3.13/_frozen_importlib_external.meta.json
iris_oc_mapper/.mypy_cache/3.13/_io.data.json
iris_oc_mapper/.mypy_cache/3.13/_io.meta.json
iris_oc_mapper/.mypy_cache/3.13/_sitebuiltins.data.json
iris_oc_mapper/.mypy_cache/3.13/_sitebuiltins.meta.json
iris_oc_mapper/.mypy_cache/3.13/_typeshed/__init__.data.json
iris_oc_mapper/.mypy_cache/3.13/_typeshed/__init__.meta.json
iris_oc_mapper/.mypy_cache/3.13/_typeshed/importlib.data.json
iris_oc_mapper/.mypy_cache/3.13/_typeshed/importlib.meta.json
iris_oc_mapper/.mypy_cache/3.13/_warnings.data.json
iris_oc_mapper/.mypy_cache/3.13/_warnings.meta.json
iris_oc_mapper/.mypy_cache/3.13/abc.data.json
iris_oc_mapper/.mypy_cache/3.13/abc.meta.json
iris_oc_mapper/.mypy_cache/3.13/ast.data.json
iris_oc_mapper/.mypy_cache/3.13/ast.meta.json
iris_oc_mapper/.mypy_cache/3.13/builtins.data.json
iris_oc_mapper/.mypy_cache/3.13/builtins.meta.json
iris_oc_mapper/.mypy_cache/3.13/codecs.data.json
iris_oc_mapper/.mypy_cache/3.13/codecs.meta.json
iris_oc_mapper/.mypy_cache/3.13/collections/__init__.data.json
iris_oc_mapper/.mypy_cache/3.13/collections/__init__.meta.json
iris_oc_mapper/.mypy_cache/3.13/collections/abc.data.json
iris_oc_mapper/.mypy_cache/3.13/collections/abc.meta.json
iris_oc_mapper/.mypy_cache/3.13/contextlib.data.json
iris_oc_mapper/.mypy_cache/3.13/contextlib.meta.json
iris_oc_mapper-1.0.3.dist-info/WHEEL
iris_oc_mapper-1.0.3.dist-info/entry_points.txt
iris_oc_mapper-1.0.3.dist-info/METADATA
iris_oc_mapper-1.0.3.dist-info/RECORD
