Metadata-Version: 2.3
Name: iris-oc-mapper
Version: 1.0.3
Summary: A tool for mapping CINECA IRIS bibliographic records to OpenCitations Meta and Index datasets, with built-in utilities for interacting with IRIS data dumps.
Keywords: IRIS,OpenCitations,Mapping,Bibliometrics,Research Information Systems
Author: Leonardo Zilli
Author-email: Leonardo Zilli <leonardo.zilli@studio.unibo.it>
License: Copyright (c) 2025 Leonardo Zilli, Erica Andreose, Silvio Peroni
Classifier: Programming Language :: Python :: 3.12
Classifier: License :: OSI Approved :: MIT License
Classifier: Operating System :: OS Independent
Classifier: Topic :: Scientific/Engineering :: Information Analysis
Classifier: Intended Audience :: Science/Research
Requires-Dist: fastexcel>=0.16.0
Requires-Dist: isal>=1.8.0
Requires-Dist: jinja2>=3.1.6
Requires-Dist: pandera[polars]>=0.26.1
Requires-Dist: plotly[express]>=6.3.0
Requires-Dist: polars>=1.31.0
Requires-Dist: pyarrow>=20.0.0
Requires-Dist: pydantic>=2.11.9
Requires-Dist: pyyaml>=6.0.2
Requires-Dist: typer>=0.17.4
Requires-Python: >=3.12
